setup.py
brynq_sdk_azure_service_bus/__init__.py
brynq_sdk_azure_service_bus/service_bus.py
brynq_sdk_azure_service_bus.egg-info/PKG-INFO
brynq_sdk_azure_service_bus.egg-info/SOURCES.txt
brynq_sdk_azure_service_bus.egg-info/dependency_links.txt
brynq_sdk_azure_service_bus.egg-info/not-zip-safe
brynq_sdk_azure_service_bus.egg-info/requires.txt
brynq_sdk_azure_service_bus.egg-info/top_level.txt