Metadata-Version: 1.0
Name: brynq-sdk-azure-service-bus
Version: 2.0.0
Summary: Azure Service Bus wrapper from BrynQ
Home-page: UNKNOWN
Author: BrynQ
Author-email: support@brynq.com
License: BrynQ License
Platform: UNKNOWN
